Metadata-Version: 2.1
Name: easycolors
Version: 1.0.2
Summary: A simple tool for convinient rgb-tuple use
Home-page: UNKNOWN
Author: Sjoerd Vermeulen
Author-email: sjoerd@marsenaar.com
License: UNKNOWN
Platform: UNKNOWN
Classifier: Programming Language :: Python :: 3
Classifier: License :: OSI Approved :: MIT License
Classifier: Operating System :: OS Independent
Requires-Python: >=3.6
